spyse/__init__.py
spyse/spyse.py
spyse.py-0.13.3.9.data/scripts/spyse
spyse.py-0.13.3.9.dist-info/LICENSE
spyse.py-0.13.3.9.dist-info/METADATA
spyse.py-0.13.3.9.dist-info/WHEEL
spyse.py-0.13.3.9.dist-info/top_level.txt
spyse.py-0.13.3.9.dist-info/RECORD
