Metadata-Version: 2.1
Name: spyse.py
Version: 0.13.3.9
Summary: API wrapper & client for spyse.com
Home-page: https://github.com/zeropwn/spyse.py
Author: Dominik Penner
Author-email: zer0pwn@riseup.net
License: UNKNOWN
Keywords: spyse spyse.py spyse.com zeropwn zer0pwn recon
Platform: UNKNOWN
Requires-Dist: requests
